niflheim_x/__init__.py
niflheim_x/core/__init__.py
niflheim_x/core/agent.py
niflheim_x/core/memory.py
niflheim_x/core/orchestrator.py
niflheim_x/core/tools.py
niflheim_x/core/types.py
niflheim_x/enterprise/observability.py
niflheim_x/enterprise/protocols.py
niflheim_x/enterprise/workflows.py
niflheim_x/llms/__init__.py
niflheim_x/llms/anthropic.py
niflheim_x/llms/base.py
niflheim_x/llms/openai.py
niflheim_x-0.1.0.dist-info/licenses/LICENSE
niflheim_x-0.1.0.dist-info/METADATA
niflheim_x-0.1.0.dist-info/WHEEL
niflheim_x-0.1.0.dist-info/top_level.txt
niflheim_x-0.1.0.dist-info/RECORD
