Metadata-Version: 2.4
Name: niflheim-x
Version: 0.1.0
Summary: A lightweight, composable Agent Orchestration Framework - the fast alternative to LangChain
Author-email: Ahmed KHI <ahmed@khitech.dev>
Maintainer-email: Ahmed KHI <ahmed@khitech.dev>
License: MIT
Project-URL: Homepage, https://github.com/Ahmed-KHI/niflheim-x
Project-URL: Repository, https://github.com/Ahmed-KHI/niflheim-x
Project-URL: Documentation, https://github.com/Ahmed-KHI/niflheim-x#readme
Project-URL: Bug Tracker, https://github.com/Ahmed-KHI/niflheim-x/issues
Keywords: ai,agents,llm,orchestration,framework,python
Classifier: Development Status :: 4 - Beta
Classifier: Intended Audience :: Developers
Classifier: License :: OSI Approved :: MIT License
Classifier: Programming Language :: Python :: 3
Classifier: Programming Language :: Python :: 3.10
Classifier: Programming Language :: Python :: 3.11
Classifier: Programming Language :: Python :: 3.12
Classifier: Topic :: Software Development :: Libraries :: Python Modules
Classifier: Topic :: Scientific/Engineering :: Artificial Intelligence
Requires-Python: >=3.10
License-File: LICENSE
Requires-Dist: pydantic>=2.0.0
Requires-Dist: httpx>=0.24.0
Requires-Dist: typing-extensions>=4.5.0
Provides-Extra: dev
Requires-Dist: pytest>=7.0.0; extra == "dev"
Requires-Dist: pytest-asyncio>=0.21.0; extra == "dev"
Requires-Dist: pytest-cov>=4.0.0; extra == "dev"
Requires-Dist: black>=23.0.0; extra == "dev"
Requires-Dist: ruff>=0.1.0; extra == "dev"
Requires-Dist: mypy>=1.5.0; extra == "dev"
Requires-Dist: types-requests>=2.31.0; extra == "dev"
Requires-Dist: pre-commit>=3.0.0; extra == "dev"
Provides-Extra: sqlite
Requires-Dist: aiosqlite>=0.19.0; extra == "sqlite"
Provides-Extra: vector
Requires-Dist: numpy>=1.24.0; extra == "vector"
Requires-Dist: faiss-cpu>=1.7.4; extra == "vector"
Dynamic: license-file
